{
    "Laborer": {
        "Barber": {"armor": "Tunic", "weapon": "Razor", "shield": "False"},
        "Bath Attendant": {"armor": "Tunic", "weapon": "Dagger", "shield": "False"},
        "Bricklayer": {"armor": "Tunic", "weapon": "Hammer", "shield": "False"},
        "Cook": {"armor": "Tunic", "weapon": "Chef's Knife", "shield": "False"},
        "Dockworker": {"armor": "Tunic", "weapon": "Dagger", "shield": "False"},
        "Launderer": {"armor": "Tunic", "weapon": "Dagger", "shield": "False"},
        "Rower": {"armor": "Tunic", "weapon": "Oar", "shield": "False"},
        "Gongfarmer": {"armor": "Tunic", "weapon": "Dagger", "shield": "False"},
        "Hawker": {"armor": "Tunic", "weapon": "Dagger", "shield": "False"},
        "Stablehand": {"armor": "Tunic", "weapon": "Whip", "shield": "False"},
        "Servant": {"armor": "Tunic", "weapon": "Dagger", "shield": "False"},
        "Brazen Strumpet": {"armor": "Tunic", "weapon": "Dagger", "shield": "False"},
        "Ratcatcher": {"armor": "Tunic", "weapon": "Staff", "shield": "False"},
        "Roofer": {"armor": "Tunic", "weapon": "Dagger", "shield": "False"},
        "Sailor": {"armor": "Tunic", "weapon": "Scimitar", "shield": "False"},
        "Scullion": {"armor": "Tunic", "weapon": "Dagger", "shield": "False"},
        "Woodcutter": {"armor": "Tunic", "weapon": "Hand Axe", "shield": "False"},
        "Teamster": {"armor": "Tunic", "weapon": "Whip"}, "shield": "False",
        "Tavenworker": {"armor": "Tunic", "weapon": "Dagger", "shield": "False"},
        "Unskilled Laborer": {"armor": "Tunic", "weapon": "Staff", "shield": "False"}
    },
    "Artisan": {
        "Clothmaker": {"armor": "Tunic", "weapon": "Dagger", "shield": "False"},
        "Cobbler": {"armor": "Tunic", "weapon": "Dagger", "shield": "False"},
        "Confectioner": {"armor": "Tunic", "weapon": "Dagger", "shield": "False"},
        "Cooper": {"armor": "Tunic", "weapon": "Dagger", "shield": "False"},
        "Coppersmith": {"armor": "Tunic", "weapon": "Hammer", "shield": "False"},
        "Ropemaker": {"armor": "Tunic", "weapon": "Dagger", "shield": "False"},
        "Decorative Artist": {"armor": "Tunic", "weapon": "Dagger", "shield": "False"},
        "Florist": {"armor": "Tunic", "weapon": "Dagger", "shield": "False"},
        "Gemcutter": {"armor": "Tunic", "weapon": "Dagger", "shield": "False"},
        "Glassworker": {"armor": "Tunic", "weapon": "Dagger", "shield": "False"},
        "Goldsmith": {"armor": "Tunic", "weapon": "Dagger", "shield": "False"},
        "Hornworker": {"armor": "Tunic", "weapon": "Dagger", "shield": "False"},
        "Illuminator": {"armor": "Tunic", "weapon": "Dagger", "shield": "False"},
        "Jeweler": {"armor": "Tunic", "weapon": "Dagger", "shield": "False"},
        "Locksmith": {"armor": "Tunic", "weapon": "Dagger", "shield": "False"},
        "Mason": {"armor": "Tunic", "weapon": "Hammer", "shield": "False"},
        "Parchmentmaker": {"armor": "Tunic", "weapon": "Dagger", "shield": "False"},
        "Perfumer": {"armor": "Tunic", "weapon": "Dagger", "shield": "False"},
        "Potter": {"armor": "Tunic", "weapon": "Dagger", "shield": "False"},
        "Saddler": {"armor": "Tunic", "weapon": "Dagger", "shield": "False"},
        "Scribe": {"armor": "Tunic", "weapon": "Dagger", "shield": "False"},
        "Shipwright": {"armor": "Tunic", "weapon": "Dagger", "shield": "False"},
        "Silversmith": {"armor": "Tunic", "weapon": "Dagger", "shield": "False"},
        "Spinner": {"armor": "Tunic", "weapon": "Dagger", "shield": "False"},
        "Tailor": {"armor": "Tunic", "weapon": "Dagger", "shield": "False"},
        "Tanner": {"armor": "Tunic", "weapon": "Dagger", "shield": "False"},
        "Taxidermist": {"armor": "Tunic", "weapon": "Dagger", "shield": "False"},
        "Tinker": {"armor": "Tunic", "weapon": "Dagger", "shield": "False"},
        "Wainwright": {"armor": "Tunic", "weapon": "Dagger", "shield": "False"},
        "Weaponsmith": {"armor": "Tunic", "weapon": "Hammer", "shield": "False"},
        "Wheelwright": {"armor": "Tunic", "weapon": "Dagger", "shield": "False"}
    },
    "Merchant": {
        "Bookseller": {"armor": "Tunic", "weapon": "Dagger", "shield": "False"},
        "Chandler": {"armor": "Tunic", "weapon": "Dagger", "shield": "False"},
        "Coppermonger": {"armor": "Tunic", "weapon": "Dagger", "shield": "False"},
        "Cornmonger": {"armor": "Tunic", "weapon": "Dagger", "shield": "False"},
        "Draper": {"armor": "Tunic", "weapon": "Dagger", "shield": "False"},
        "Fishmonger": {"armor": "Tunic", "weapon": "Hook", "shield": "False"},
        "Fripperer": {"armor": "Tunic", "weapon": "Dagger", "shield": "False"},
        "Furrier": {"armor": "Tunic", "weapon": "Dagger", "shield": "False"},
        "Greengrocer": {"armor": "Tunic", "weapon": "Dagger", "shield": "False"},
        "Horsemonger": {"armor": "Tunic", "weapon": "Dagger", "shield": "False"},
        "Ironmonger": {"armor": "Tunic", "weapon": "Dagger", "shield": "False"},
        "Lawyer": {"armor": "Tunic", "weapon": "Dagger", "shield": "False"},
        "Lumbermonger": {"armor": "Tunic", "weapon": "Hand Axe", "shield": "False"},
        "Mercer": {"armor": "Tunic", "weapon": "Dagger", "shield": "False"},
        "Oilmonger": {"armor": "Tunic", "weapon": "Dagger", "shield": "False"},
        "Skinner": {"armor": "Tunic", "weapon": "Dagger", "shield": "False"},
        "Poulterer": {"armor": "Tunic", "weapon": "Dagger", "shield": "False"},
        "Salter": {"armor": "Tunic", "weapon": "Dagger", "shield": "False"},
        "Vintner": {"armor": "Tunic", "weapon": "Dagger", "shield": "False"}
    },
    "Specialist": {
        "Alchemist": {"armor": "Tunic", "weapon": "Dagger", "shield": "False"},
        "Animal Trainer": {"armor": "Tunic", "weapon": "Whip", "shield": "False"},
        "Artillerist": {"armor": "Leather Armor", "weapon": "Short Sword","shield": "False"},
        "Engineer": {"armor": "Tunic", "weapon": "Dagger", "shield": "False"},
        "Healer": {"armor": "Tunic", "weapon": "Staff"}, "shield": "False",
        "Marshal": {"armor": "Chain Mail", "weapon": "Short Sword","shield": "False"},
        "Navigator": {"armor": "Tunic", "weapon": "Dagger","shield": "False"},
        "Quartermaster": {"armor": "Tunic", "weapon": "Short Sword","shield": "False"},
        "Sage": {"armor": "Tunic", "weapon": "Staff","shield": "False"},
        "Siege Engineer": {"armor": "Leather Armor", "weapon": "Short Sword","shield": "False"},
        "Ship Captain": {"armor": "Leather Armor", "weapon": "Scimitar","shield": "False"}
    },
    "Hosteller": {
        "Sly Pimp": {"armor": "Tunic", "weapon": "Dagger","shield": "False"},
        "Cantinakeeper": {"armor": "Tunic", "weapon": "Dagger","shield": "False"},
        "Innkeeper": {"armor": "Tunic", "weapon": "Dagger","shield": "False"},
        "Tavernkeeper": {"armor": "Tunic", "weapon": "Dagger","shield": "False"}
    },
    "Entertainer": {
        "Actor": {"armor": "Tunic", "weapon": "Dagger","shield": "False"},
        "Dancer": {"armor": "Tunic", "weapon": "Dagger","shield": "False"},
        "Musician": {"armor": "Tunic", "weapon": "Dagger","shield": "False"},
        "Singer": {"armor": "Tunic", "weapon": "Dagger","shield": "False"},
        "Carouser": {"armor": "Tunic", "weapon": "Dagger","shield": "False"},
        "Haughty Courtesan": {"armor": "Tunic", "weapon": "Dagger","shield": "False"}
    },
    "Mercenary": {
        "Light Infantry": {"armor": "Leather Armor", "weapon": "Short Sword","shield": "True"},
        "Heavy Infantry": {"armor": "Banded Plate Armor", "weapon": "Spear","shield": "True"},
        "Slinger": {"armor": "Tunic", "weapon": "Sling","shield": "True"},
        "Bowman": {"armor": "Leather Armor", "weapon": "Short Bow","shield": "False"},
        "Crossbowman": {"armor": "Chain Mail", "weapon": "Crossbow","shield": "False"},
        "Composite Bowman": {"armor": "Leather Armor", "weapon": "Composite Bow","shield": "False"},
        "Longbowman": {"armor": "Chain Mail", "weapon": "Long Bow","shield": "False"},
        "Light Cavalry": {"armor": "Leather Armor", "weapon": "Sword","shield": "True"},
        "Mounted Crossbowman": {"armor": "Plate Armor", "weapon": "Crossbow","shield": "False"},
        "Horse Archer": {"armor": "Leather Armor", "weapon": "Composite Bow","shield": "False"},
        "Medium Cavalry": {"armor": "Lamellar", "weapon": "Lance","shield": "True"},
        "Heavy Cavalry": {"armor": "Plate Armor", "weapon": "Lance","shield": "True"},
        "Cataphract Cavalry": {"armor": "Plate Armor", "weapon": "Lance","shield": "True"},
        "Camel Archer": {"armor": "Leather Armor", "weapon": "Composite Bow","shield": "False"},
        "Camel Lancer": {"armor": "Chain Mail", "weapon": "Lance","shield": "True"}
    },
    "Ecclestiac": {
        "Missionary": {"armor": "Cassock", "weapon": "Staff","shield": "False"},
        "Anchorite": {"armor": "Cassock", "weapon": "Dagger","shield": "False"},
        "Heretic": {"armor": "Cassock", "weapon": "Dagger","shield": "False"},
        "Medician": {"armor": "Cassock", "weapon": "Dagger","shield": "False"},
        "Inquisitor": {"armor": "Cassock", "weapon": "Dagger","shield": "False"},
        "Oracle": {"armor": "Cassock", "weapon": "Staff","shield": "False"},
        "Sacred Courtesan": {"armor": "Cassock", "weapon": "Dagger","shield": "False"},
        "Seminarian": {"armor": "Cassock", "weapon": "Staff","shield": "False"},
        "Village Witch": {"armor": "Cassock", "weapon": "Dagger","shield": "False"}
    },
    "Magician": {
        "Apprentice Mage": {"armor": "Cassock", "weapon": "Staff","shield": "False"},
        "Apprentice Warlock": {"armor": "Cassock", "weapon": "Staff","shield": "False"},
        "Astrologer": {"armor": "Cassock", "weapon": "Staff","shield": "False"},
        "Augur": {"armor": "Cassock", "weapon": "Staff","shield": "False"},
        "Charlatan": {"armor": "Cassock", "weapon": "Dagger","shield": "False"},
        "Failed Apprentice": {"armor": "Cassock", "weapon": "Staff","shield": "False"},
        "Hedge Magician": {"armor": "Cassock", "weapon": "Staff","shield": "False"},
        "Occultist": {"armor": "Cassock", "weapon": "Dagger","shield": "False"},
        "Prestidigitator": {"armor": "Cassock", "weapon": "Staff","shield": "False"}
    }
}